nerwhal/__init__.py
nerwhal/combination_strategies.py
nerwhal/core.py
nerwhal/entity_aligner.py
nerwhal/nlp_utils.py
nerwhal/scorer.py
nerwhal/tokenizer.py
nerwhal/types.py
nerwhal/backends/__init__.py
nerwhal/backends/base.py
nerwhal/backends/entity_ruler_backend.py
nerwhal/backends/flashtext_backend.py
nerwhal/backends/re_backend.py
nerwhal/backends/stanza_ner_backend.py
nerwhal/integrated_recognizers/__init__.py
nerwhal/integrated_recognizers/email_recognizer.py
nerwhal/integrated_recognizers/money_recognizer.py
nerwhal/integrated_recognizers/number_recognizer.py
nerwhal/integrated_recognizers/phone_number_recognizer.py
nerwhal/integrated_recognizers/de/__init__.py
nerwhal/integrated_recognizers/de/de_country_recognizer.py
nerwhal/integrated_recognizers/de/de_date_recognizer.py
nerwhal/integrated_recognizers/de/data/countries.csv
nerwhal/recognizer_bases/__init__.py
nerwhal/recognizer_bases/base.py
nerwhal/recognizer_bases/entity_ruler_recognizer.py
nerwhal/recognizer_bases/flashtext_recognizer.py
nerwhal/recognizer_bases/re_recognizer.py
tests/backends/__init__.py
tests/backends/test_entity_ruler_backend.py
tests/backends/test_flashtext_backend.py
tests/backends/test_re_backend.py
tests/backends/test_stanza_ner_backend.py
tests/integrated_recognizers/__init__.py
tests/integrated_recognizers/conftest.py
tests/integrated_recognizers/test_email_recognizer.py
tests/integrated_recognizers/test_money_recognizer.py
tests/integrated_recognizers/test_number_recognizer.py
tests/integrated_recognizers/test_phone_number_recognizer.py
tests/integrated_recognizers/de/__init__.py
tests/integrated_recognizers/de/test_de_country_recognizer.py
tests/integrated_recognizers/de/test_de_date_recognizer.py
nerwhal-0.1.2.dist-info/LICENSE
nerwhal-0.1.2.dist-info/METADATA
nerwhal-0.1.2.dist-info/WHEEL
nerwhal-0.1.2.dist-info/top_level.txt
nerwhal-0.1.2.dist-info/RECORD
