Metadata-Version: 2.1
Name: nerwhal
Version: 0.1.2
Summary: Find personally identifiable information in German texts using NER and rule based matching.
Home-page: https://openredact.org/
Author: Jonas Langhabel
Author-email: hello@openredact.org
License: MIT
Platform: UNKNOWN
Requires-Python: >=3.7
License-File: LICENSE
Requires-Dist: spacy (<3.0.0,>=2.3.2)
Requires-Dist: stanza (<1.1.0,>=1.0.1)
Requires-Dist: torch (<1.6.0,>=1.3.0)
Requires-Dist: flashtext (<3.0,>=2.7)
Requires-Dist: pydantic (<2.0.0,>=1.0.0)
